MANIFEST.in
l10n_hr_chart_template.xml
l10n_hr_wizard.xml
setup.py
./__init__.py
./__openerp__.py
data/account.account.template.csv
data/account.account.type.csv
data/account.tax.code.template.csv
data/account.tax.template.csv
data/fiscal_position_template.xml
openerp_l10n_hr.egg-info/PKG-INFO
openerp_l10n_hr.egg-info/SOURCES.txt
openerp_l10n_hr.egg-info/dependency_links.txt
openerp_l10n_hr.egg-info/requires.txt
openerp_l10n_hr.egg-info/top_level.txt
static/src/img/icon.png